VFM_Code/LSTM_example.py
VFM_Code/__init__.py
VFM_Code/make_dataframes.py
VFM_IRP_ACSE9-1.0.dist-info/METADATA
VFM_IRP_ACSE9-1.0.dist-info/WHEEL
VFM_IRP_ACSE9-1.0.dist-info/top_level.txt
VFM_IRP_ACSE9-1.0.dist-info/RECORD
