Metadata-Version: 2.1
Name: VFM-IRP-ACSE9
Version: 1.0
Summary: Individual MSc Project
Home-page: https://github.com/acse-2019/irp-acse-nt719/tree/master/Code/
Author: Nicolas Trinephi
Author-email: nicolas.trinephi@imperial.ac.uk
License: xxxxxxxxxxxxxxxxxxxxxxxxxxxx
Platform: UNKNOWN
